importFromParent/__init__.py
importFromParent-0.0.9.dist-info/LICENSE.txt
importFromParent-0.0.9.dist-info/METADATA
importFromParent-0.0.9.dist-info/WHEEL
importFromParent-0.0.9.dist-info/top_level.txt
importFromParent-0.0.9.dist-info/RECORD
