Metadata-Version: 2.1
Name: importFromParent
Version: 0.0.9
Summary: import a package or a module from a py file's parent.
Home-page: https://www.youtube.com/channel/UCAbwAklWIeuoKKjVBMQVCew
Author: Cauã S. C. P.
Author-email: cauascp37@gmail.com
License: UNKNOWN
Platform: UNKNOWN
Classifier: Programming Language :: Python :: 3
Classifier: License :: OSI Approved :: MIT License
Classifier: Operating System :: OS Independent
Requires-Python: >=3.6
